{"name": "Jim Schwoebel", "email": "jim.schwoebel@gmail.com", "userID": 0, "hostdir": "/Users/jimschwoebel/Desktop/nala/data/baseline/Jim Schwoebel_faces", "location": {"ip": "205.201.18.70", "city": "Cambridge", "region": "Massachusetts", "country": "US", "loc": "42.3700,-71.0812", "postal": "02141", "org": "AS395354 Starry, Inc."}, "rest time": 0.1, "facenums": 0, "registration date": "2018-07-05 22:05:37.796121", "logins": ["2018-07-05 22:05:37.799756", "2018-07-05 22:06:35.714964", "2018-07-05 22:08:47.829538", "2018-07-05 22:10:47.837581", "2018-07-05 22:21:14.227310"], "logouts": [], "sessions": [[[[[[]]]]]], "query count": 0, "queries": [[[[[[]]]]]], "noise": [[[[[[]]]]]], "action count": [[[[[0]]]]], "action log": [[[[[[]]]]]], "available actions": ["social.py", "events.py", "alarm.py", "weather.py", "music.py", "exercise.py", "espn.py", "nutrition.py", "coffeebreak.py", "search.py", "plan_trip.py", "grateful.py", "meditation.py", "news.py"], "google tts": "en-US-Wavenet-C", "loopnum": 1}